weiser/__init__.py
weiser/checks/__init__.py
weiser/checks/anomaly.py
weiser/checks/base.py
weiser/checks/numeric.py
weiser/drivers/__init__.py
weiser/drivers/base.py
weiser/drivers/bigquery.py
weiser/drivers/databricks.py
weiser/drivers/metric_stores/README.md
weiser/drivers/metric_stores/__init__.py
weiser/drivers/metric_stores/duckdb.py
weiser/drivers/metric_stores/migrations/README.md
weiser/drivers/metric_stores/migrations/__init__.py
weiser/drivers/metric_stores/migrations/base_migration.py
weiser/drivers/metric_stores/migrations/migration_runner.py
weiser/drivers/metric_stores/migrations/versions/20250711_083256_add_id_column.py
weiser/drivers/metric_stores/migrations/versions/20250711_184700_add_tenant_id_column.py
weiser/drivers/metric_stores/migrations/versions/__init__.py
weiser/drivers/metric_stores/models.py
weiser/drivers/metric_stores/models_duckdb.py
weiser/drivers/metric_stores/postgres.py
weiser/drivers/mysql.py
weiser/drivers/postgres.py
weiser/drivers/snowflake.py
weiser/loader/__init__.py
weiser/loader/config.py
weiser/loader/export.py
weiser/loader/models.py
weiser/main.py
weiser/runner/__init__.py
weiser_ai-0.2.2.dist-info/METADATA
weiser_ai-0.2.2.dist-info/WHEEL
weiser_ai-0.2.2.dist-info/entry_points.txt
weiser_ai-0.2.2.dist-info/licenses/LICENSE
weiser_ai-0.2.2.dist-info/RECORD
