Metadata-Version: 2.4
Name: weiser-ai
Version: 0.2.2
Summary: Enterprise-grade data quality framework with YAML configuration, LLM-friendly design, and advanced statistical validation
Keywords: data-quality,data-validation,data-testing,sql,yaml,llm,ai
Author-Email: Paco Valdez <paco.valdez@berkeley.edu>
Maintainer-Email: Paco Valdez <paco.valdez@berkeley.edu>
License-Expression: MIT
Classifier: Development Status :: 4 - Beta
Classifier: Intended Audience :: Developers
Classifier: Intended Audience :: Information Technology
Classifier: Programming Language :: Python :: 3
Classifier: Programming Language :: Python :: 3.10
Classifier: Programming Language :: Python :: 3.11
Classifier: Programming Language :: Python :: 3.12
Classifier: Topic :: Database
Classifier: Topic :: Software Development :: Quality Assurance
Classifier: Topic :: Software Development :: Testing
Classifier: Typing :: Typed
Project-URL: Homepage, https://weiser.ai
Project-URL: Documentation, https://weiser.ai
Project-URL: Repository, https://github.com/weiser-ai/weiser-ai
Project-URL: Bug Tracker, https://github.com/weiser-ai/weiser-ai/issues
Requires-Python: <3.13,>=3.10
Requires-Dist: typer[all]>=0.9.0
Requires-Dist: sqlglotrs==0.1.0
Requires-Dist: pydantic>=2.5.3
Requires-Dist: sqlalchemy>=2.0.41
Requires-Dist: sqlmodel>=0.0.24
Requires-Dist: alembic>=1.16.4
Requires-Dist: duckdb>=1.2.0
Requires-Dist: jinja2>=3.1.2
Requires-Dist: python-dotenv>=1.0.0
Requires-Dist: psycopg2>=2.9.5
Requires-Dist: pandas>=2.2.2
Requires-Dist: boto3>=1.35.49
Requires-Dist: sqlglot==20.5.0
Requires-Dist: pyyaml==6.0.2
Requires-Dist: slack-sdk>=3.34.0
Requires-Dist: snowflake-sqlalchemy>=1.7.5
Requires-Dist: databricks-sqlalchemy>=2.0.7
Requires-Dist: sqlalchemy-bigquery>=1.13.0
Requires-Dist: PyMySQL>=1.0.2
Requires-Dist: duckdb-engine>=0.17.0
